view_animator/__init__.py
view_animator/base_animator.py
view_animator/pybullet_animator.py
view_animator/rviz_animator.py
view_animator-0.1.0.dist-info/LICENSE.txt
view_animator-0.1.0.dist-info/METADATA
view_animator-0.1.0.dist-info/WHEEL
view_animator-0.1.0.dist-info/top_level.txt
view_animator-0.1.0.dist-info/RECORD
