Metadata-Version: 2.1
Name: view-animator
Version: 0.1.0
Summary: Animate the camera view for a variety of environments
Author-email: Sheng Zhong <zhsh@umich.edu>
Maintainer-email: Sheng Zhong <zhsh@umich.edu>
License: Copyright (c) Sheng Zhong
Project-URL: Homepage, https://github.com/LemonPi/view_animator
Project-URL: Bug Reports, https://github.com/LemonPi/view_animator/issues
Project-URL: Source, https://github.com/LemonPi/view_animator
Keywords: camera,animation,visualization,simulation
Classifier: Development Status :: 4 - Beta
Classifier: Intended Audience :: Developers
Classifier: Topic :: Multimedia :: Video
Classifier: Topic :: Games/Entertainment :: Simulation
Classifier: License :: OSI Approved :: MIT License
Classifier: Programming Language :: Python :: 3
Classifier: Programming Language :: Python :: 3 :: Only
Requires-Python: >=3.6
License-File: LICENSE.txt
Provides-Extra: pybullet
Requires-Dist: pybullet ; extra == 'pybullet'
